{
    "userArray": [
        {
            "testusername": "idsb3t4@us.ibm.com",
            "testpassword": "JhubPa88_0122",
            "organization_guid": "8a5b49de-1a3c-4075-b3ec-bd25d90ae2a1"
        },
        {
            "testusername": "idsb3t2@us.ibm.com",
            "testpassword": "JhubPa88_0122",
            "organization_guid": "9545845d-4f88-4979-a5c8-279240c7377a"
        }
    ],
    "auth-header": "Y2Y6",
    "slack-token":"xoxp-13948444357-13953293954-13959136117-fb748ccba5"
}